{"id": 170, "slug": "the-part-that-freezes-in-intimacy", "title": "The Part That Freezes in Intimacy", "category": "the-parts", "categoryName": "The Parts", "dateISO": "2026-04-24T12:00:00Z", "wordCount": 2623, "readingTime": 10, "openerType": "named-reference", "faqCount": 3, "backlinkType": "kalesh", "conclusionType": "tender", "researcherName": "Sadhguru", "researcherTopic": "yoga and consciousness, the mechanics of the mind", "externalSites": [], "phraseIndices": [26, 9, 19, 24, 11], "heroImage": "https://shattered-armor.b-cdn.net/images/hero-170.webp", "ogImage": "https://shattered-armor.b-cdn.net/images/og-170.webp", "metaDescription": "Explore why the body freezes in intimacy as a trauma response. Learn how to understand this protective mechanism and gently guide your nervous system back to safety.", "imageDescription": "A pair of hands gently hold a luminous, golden thread, weaving it through a complex, abstract pattern of light. The background is soft and warm, suggesting the delicate and intricate process of healing the nervous system.", "finalH2": "The Tender Return", "generatedWordCount": 2650, "openerStartsWithYou": "", "htmlContent": "Sadhguru, in his explorations of consciousness, often speaks of the intricate ways our inner world is constructed\u2014not from grand ideas, but from the raw data of our lived experience. This is the territory where the body holds a memory the thinking mind has tried to dismiss, where a gentle touch can feel less like an invitation and more like a threat. We are not reacting to the present moment, but to a ghost-memory superimposed upon it, a neurological echo from a time when closeness was linked with danger. The freeze response that descends is not a decision; it is a physiological inheritance, an intelligent system activating a survival protocol that has outlived its original context.\n\nIt is a profound and disorienting experience to find one part of oneself slamming on the brakes just as another yearns to connect, a silent veto from the deepest strata of the nervous system. This internal schism isn\u2019t a sign of being broken, but evidence of an outdated form of self-protection. In my years working in this territory, I\u2019ve seen countless individuals describe this exact phenomenon: the sudden internal deadness, the feeling of watching oneself from a distance, the inability to access the warmth they so deeply desire. Understanding this freeze response is not about fighting it, but about learning its language, its history, and its logic, for it is a part of the self ensuring survival based on an old map of the world.\n\n## The Architecture of the Freeze\n\nThe freeze response, the least understood of the primary survival strategies, is a state of profound immobilization, a biological shutdown when fight or flight are deemed impossible. It\u2019s a state of suspended animation where metabolic processes slow and a sense of disconnection takes over\u2014a neurological disappearing act. This is not a conscious choice but a powerful, primitive reflex of the dorsal vagal part of our autonomic nervous system. When this system takes over, it plunges the body into a state of conservation to numb the overwhelming. For those with a history of complex trauma, this response can become a default setting, a well-worn groove the nervous system slips into whenever it perceives a threat in intimacy.\n\nIf our early experiences involved consistent safety, our nervous system learns to play a wide range of relational music. But if the early environment was characterized by unpredictability or danger, the instrument becomes tuned for survival, learning that other people can be sources of profound dysregulation. The result is a system exquisitely sensitive to cues of danger\u2014a certain tone of voice, a particular look\u2014and is quick to deploy its most powerful defensive strategy. The freeze that shows up in intimacy is the body\u2019s memory of a time when becoming still and invisible was the only way to endure the unendurable. It is a testament to what was survived, not a defect in the present.\n\n> The body remembers what the mind would prefer to file away.\n\nThis is not a metaphor; it is a neurological fact. The implicit memories stored in the body do not operate on a timeline; they are simply present, ready to be activated by corresponding sensory input. The work is not to erase these memories, but to build a present-day nervous system with a greater capacity to stay online, to recognize the map it is reading is old, and to slowly introduce new data that proves the current territory is safe. How do we begin to update a system that operates outside the realm of language and logic?\n\n## The Predictive Brain and the Cost of Closeness\n\nOur brains are not passive observers; they are active, predictive engines, constantly generating a model of the world based on past experiences to anticipate what happens next. This process is incredibly efficient, but when calibrated by trauma, it becomes biased toward threat. It predicts danger not as a possibility, but as an inevitability, especially in the vulnerable territory of human connection. The anxiety that accompanies the freeze response is the sound of this predictive engine working overtime, running countless simulations of potential harm.\n\n> The brain is prediction machinery. Anxiety is just prediction running without a stop button.\n\nThis is why attempts to \u201cthink\u201d our way out of a freeze response are so often futile. We are trying to use the neocortex to argue with an older, faster system that is already convinced of the verdict. The body has been sentenced to immobilization before the conscious mind has had a chance to present its case. A client once described this as a courtroom where the trial is a sham, the outcome decided long before any evidence is presented. The feeling of being close to someone becomes the trigger for a cascade of predictions about abandonment or betrayal. The freeze is the body\u2019s way of bracing for an impact it believes is already on its way.\n\nThe implication: we can see the path forward, not as a battle against the brain\u2019s predictions, but as a gentle offering of new, contradictory evidence. We cannot simply tell the system it is safe; we must offer it the felt experience of safety, moment by moment. This is the slow work of relational repair, both with others and within ourselves. It involves learning to track the subtle shifts in our own physiology, to notice the first whisper of a shutdown before it becomes a full-blown freeze. It is the work of building dual awareness\u2014the ability to be with the memory of the past threat while simultaneously staying connected to the reality of the present safety. We learn to have one foot in the trauma-memory and one foot in the here and now, and to tolerate the dissonance without collapsing. This is not about getting rid of the prediction, but about learning not to treat it as a prophecy. We can learn more by exploring how to <a href=\"/article/reparenting-the-inner-child\">reparent the inner child</a>.\n\n## The Difference Between Aloneness and Being With Yourself\n\nFor many who have experienced the freeze response in intimacy, being alone can feel like the only truly safe state. Aloneness removes the primary variable the nervous system has learned to associate with danger: the other person. In solitude, the predictive brain can quiet down, hypervigilance can soften, and a sense of baseline regulation can be achieved. Yet, there is a profound distinction between the circumstantial state of being alone and the active, intentional practice of being with oneself. One is an escape from a perceived threat; the other is a cultivation of internal safety.\n\nBeing alone is often a strategy of avoidance, a movement away from the dysregulation that connection can provoke. While necessary at times, if it becomes the only strategy, it reinforces the underlying belief that intimacy is inherently dangerous, keeping the world small. Being with oneself, on the other hand, is a movement toward. It is the practice of turning one\u2019s attention inward with curiosity and without judgment. It is learning to offer the same quality of presence to our own inner world that we might hope to receive from a trusted other. It is the work of becoming our own secure base.\n\n> There's a difference between being alone and being with yourself. One is circumstance. The other is practice.\n\nThis practice is the foundation for developing the capacity to be with another person without losing oneself. It involves learning to sit with the discomfort of our own sensations and emotions without needing to immediately fix or escape them. It is the cultivation of an internal anchor that can hold steady even when the storms of relational activation gather. When we have developed this capacity to be with ourselves, we are no longer dependent on the other person to regulate us, nor are we as terrified of their potential to dysregulate us. We have a place to return to within ourselves. This internal stability is crucial for anyone navigating the complexities of <a href=\"/article/the-four-f-trauma-responses\">the four F trauma responses</a>.\n\n## The Reorganization of Perception\n\nThe journey of healing from complex trauma is not one of erasure, but of integration. It is not about getting rid of the parts of us that freeze, but about welcoming them into a larger, more compassionate internal system. Trauma disorganizes our perception of ourselves, others, and the world. It shatters our sense of continuity, leaving us with a fragmented inner landscape where different parts hold different beliefs, memories, and survival strategies. The part that freezes in intimacy is one such fragment, stuck in a time when this response was essential.\n\nRecovery, then, is the process of reorganizing this inner world, but this time with our conscious and compassionate participation. It is the work of becoming the loving witness to our own experience, of extending understanding to the parts of us we have long judged or feared. This is not a passive process; it is an active and courageous one. It requires us to turn toward the very experiences we have spent a lifetime trying to avoid. It is the slow, patient work of stitching the self back together, not to erase the seams, but to honor the story they tell.\n\n> Trauma reorganizes perception. Recovery reorganizes it again, but this time with your participation.\n\nThis reorganization is what allows us to move from being chronically triggered by the past to being mindfully present in the now. It is what allows us to see a partner\u2019s outstretched hand not as a threat, but as an invitation, to feel the warmth of connection without the simultaneous terror of annihilation. This process is often supported by therapeutic modalities that work directly with the body and the nervous system, such as Somatic Experiencing, which help to complete the thwarted survival responses stored in the body. It is also deeply supported by a personal practice of mindfulness and self-compassion, which builds the internal resources needed to navigate this challenging terrain. For those interested in the mechanics of this, exploring the <a href=\"/article/understanding-polyvagal-theory\">polyvagal ladder</a> can be a profound step.\n\n## The Paradox of Acceptance in Intimacy\n\nThe impulse to fight the freeze response is understandable. It feels like a barrier to connection. We try to push through it, reason with it, or shame it into submission, believing that if we just try hard enough, we can overcome it. Yet, this very struggle often perpetuates the cycle. The internal battle against the freeze response is, to the nervous system, just another threat. It reinforces the sense of being unsafe, of being at war with oneself. The more we fight the freeze, the more the system doubles down on its strategy of immobilization. It is a perfect and painful loop.\n\nPay attention to the mechanism: we encounter one of the most profound and counterintuitive principles of this work. The path out of the freeze is not through resistance, but through acceptance. This is not a passive resignation to a life without intimacy, but an active, courageous, and compassionate turning toward the reality of our present experience. It is the willingness to be with the freeze without demanding it be different. It is the practice of offering a quality of unconditional presence to this part of ourselves, a presence that says, \u201cI see you. I feel you. I am not going to abandon you.\u201d\n\n> The paradox of acceptance is that nothing changes until you stop demanding that it does.\n\nWhen we meet the freeze with this quality of acceptance, something remarkable begins to happen. The nervous system registers a new experience: being met with presence instead of struggle. This is a powerful dose of safety. It is the beginning of a new relational pattern, first within ourselves, and then, by extension, with others. When we stop fighting the freeze, we are no longer adding a layer of self-abandonment to the original wound. We are, for the first time, staying with ourselves in the midst of the shutdown. This is the very definition of self-compassion in action. This is a core teaching in many contemplative traditions, and you can learn more about it through the work of teachers who explore <a href=\"https://kalesh.love\">healing and consciousness</a>.\n\n## Frequently Asked Questions\n\n### Why does my body freeze when I want to be close to someone?\n\nThis response is a deeply ingrained survival mechanism rooted in the oldest part of our nervous system, the dorsal vagal complex. When your system perceives a threat\u2014even a subtle one based on past experiences with intimacy\u2014it can trigger an involuntary immobilization or \u201cfreeze\u201d state as a form of self-protection. It\u2019s not a conscious choice or a reflection of your desire for connection, but rather your body\u2019s memory of a time when becoming still and numb was the safest option. The work is to gently teach your nervous system that the present moment of connection is different from the past.\n\n### Can I ever get rid of this freeze response?\n\nThe goal is not to eliminate the freeze response, as it is a natural and essential part of our survival toolkit. Instead, the work is to increase your nervous system\u2019s capacity and flexibility so that freezing is no longer the default reaction to intimacy. Through practices like somatic awareness, mindfulness, and co-regulation with a safe other, you can expand your \u201cwindow of tolerance\u201d and help your system learn to stay present and engaged even when you feel vulnerable. Over time, the response becomes less frequent, less intense, and you develop the ability to move out of it with greater ease.\n\n### How can I explain this to my partner without scaring them away?\n\nCommunicating about this can be a powerful act of intimacy in itself. You might try explaining it from a place of \u201cneurobiological fact\u201d rather than personal failing. For example, you could say something like, \u201cSometimes when we get close, a very old part of my nervous system gets scared and hits the brakes. It\u2019s not about you, and it\u2019s not what I want. When it happens, what would be most helpful is if we could just pause for a moment so I can help my body feel safe again.\u201d This frames it as a shared process and invites your partner to be an ally in your healing.\n\n## The Tender Return\n\nThere is no final arrival point in this work, no graduation day from the school of the nervous system. There is only the ongoing practice of meeting what is here with a growing capacity for presence, compassion, and awareness. The part of you that freezes in intimacy is not a pathology to be cured, but a profound testament to your will to survive. It holds the memory of what was once unendurable, and it has done its job perfectly. The invitation now is not to banish this protector, but to gently and respectfully help it to understand that the war is over. The work is to introduce it to a new reality, one in which connection can be a source of nourishment rather than a threat.\n\nThis is the tender, unfolding path of coming home to oneself. It is the journey of discovering that the safety we have been seeking in others has been waiting for us all along, right here, in the quiet, unwavering presence of our own awareness. It is the slow and sacred work of learning to be with ourselves, in all our complexity, with a love that does not waver. And from that place, and only from that place, can we begin to truly meet another.\n\n> Trauma reorganizes perception. Recovery reorganizes it again, but this time with your participation.\n\nThis is the heart of the matter. The journey is not about becoming a different person, but about becoming more fully and compassionately who we already are. It is about reclaiming the parts of ourselves that have been lost in the shadows of trauma and welcoming them back into the light of our own awareness. It is a return to wholeness, not as a destination, but as a way of being in the world. And in that return, we discover a new kind of intimacy, one that is not built on the absence of fear, but on the courage to meet that fear with love.\n<p><strong>Are you willing to be uncomfortable long enough for something to shift?</strong></p>", "challengeConclusion": true}